{"nodes": [{"id": "d_freelancer_os_apps_api_src_middleware_errorhandler_ts", "label": "errorHandler.ts", "file_type": "code", "source_file": "d:\\Freelancer-os\\apps\\api\\src\\middleware\\errorHandler.ts", "source_location": "L1"}, {"id": "errorhandler_errorhandler", "label": "errorHandler()", "file_type": "code", "source_file": "d:\\Freelancer-os\\apps\\api\\src\\middleware\\errorHandler.ts", "source_location": "L4"}, {"id": "errorhandler_notfound", "label": "notFound()", "file_type": "code", "source_file": "d:\\Freelancer-os\\apps\\api\\src\\middleware\\errorHandler.ts", "source_location": "L34"}, {"id": "errorhandler_createerror", "label": "createError()", "file_type": "code", "source_file": "d:\\Freelancer-os\\apps\\api\\src\\middleware\\errorHandler.ts", "source_location": "L38"}], "edges": [{"source": "d_freelancer_os_apps_api_src_middleware_errorhandler_ts", "target": "express", "relation": "imports_from", "confidence": "EXTRACTED", "source_file": "d:\\Freelancer-os\\apps\\api\\src\\middleware\\errorHandler.ts", "source_location": "L1", "weight": 1.0}, {"source": "d_freelancer_os_apps_api_src_middleware_errorhandler_ts", "target": "zod", "relation": "imports_from", "confidence": "EXTRACTED", "source_file": "d:\\Freelancer-os\\apps\\api\\src\\middleware\\errorHandler.ts", "source_location": "L2", "weight": 1.0}, {"source": "d_freelancer_os_apps_api_src_middleware_errorhandler_ts", "target": "errorhandler_errorhandler", "relation": "contains", "confidence": "EXTRACTED", "source_file": "d:\\Freelancer-os\\apps\\api\\src\\middleware\\errorHandler.ts", "source_location": "L4", "weight": 1.0}, {"source": "d_freelancer_os_apps_api_src_middleware_errorhandler_ts", "target": "errorhandler_notfound", "relation": "contains", "confidence": "EXTRACTED", "source_file": "d:\\Freelancer-os\\apps\\api\\src\\middleware\\errorHandler.ts", "source_location": "L34", "weight": 1.0}, {"source": "d_freelancer_os_apps_api_src_middleware_errorhandler_ts", "target": "errorhandler_createerror", "relation": "contains", "confidence": "EXTRACTED", "source_file": "d:\\Freelancer-os\\apps\\api\\src\\middleware\\errorHandler.ts", "source_location": "L38", "weight": 1.0}], "raw_calls": [{"caller_nid": "errorhandler_errorhandler", "callee": "json", "source_file": "d:\\Freelancer-os\\apps\\api\\src\\middleware\\errorHandler.ts", "source_location": "L11"}, {"caller_nid": "errorhandler_errorhandler", "callee": "status", "source_file": "d:\\Freelancer-os\\apps\\api\\src\\middleware\\errorHandler.ts", "source_location": "L11"}, {"caller_nid": "errorhandler_errorhandler", "callee": "map", "source_file": "d:\\Freelancer-os\\apps\\api\\src\\middleware\\errorHandler.ts", "source_location": "L13"}, {"caller_nid": "errorhandler_errorhandler", "callee": "error", "source_file": "d:\\Freelancer-os\\apps\\api\\src\\middleware\\errorHandler.ts", "source_location": "L23"}, {"caller_nid": "errorhandler_errorhandler", "callee": "json", "source_file": "d:\\Freelancer-os\\apps\\api\\src\\middleware\\errorHandler.ts", "source_location": "L26"}, {"caller_nid": "errorhandler_errorhandler", "callee": "status", "source_file": "d:\\Freelancer-os\\apps\\api\\src\\middleware\\errorHandler.ts", "source_location": "L26"}, {"caller_nid": "errorhandler_errorhandler", "callee": "error", "source_file": "d:\\Freelancer-os\\apps\\api\\src\\middleware\\errorHandler.ts", "source_location": "L30"}, {"caller_nid": "errorhandler_errorhandler", "callee": "json", "source_file": "d:\\Freelancer-os\\apps\\api\\src\\middleware\\errorHandler.ts", "source_location": "L31"}, {"caller_nid": "errorhandler_errorhandler", "callee": "status", "source_file": "d:\\Freelancer-os\\apps\\api\\src\\middleware\\errorHandler.ts", "source_location": "L31"}, {"caller_nid": "errorhandler_notfound", "callee": "json", "source_file": "d:\\Freelancer-os\\apps\\api\\src\\middleware\\errorHandler.ts", "source_location": "L35"}, {"caller_nid": "errorhandler_notfound", "callee": "status", "source_file": "d:\\Freelancer-os\\apps\\api\\src\\middleware\\errorHandler.ts", "source_location": "L35"}]}